Workbook

Sheet Template
A1: BRAND | B1: CATEGORY | C1: SUB CATEGORY | D1: PRODUCT NAME | E1: VARIANT NAME | F1: STOCK | G1: UNIT | H1: WEIGHT | I1: LIST PRICE | J1: DISCOUNT (%) | K1: PROFIT (%) | L1: GST (%) | M1: FINAL PRICE | N1: SECONDARY THRESHOLD | O1: TERTIARY THRESHOLD | R1: List Price | S1: Discount | T1: percentage | U1: Discount | V1: Disc Amt | W1: After Disc Landing Price | Y1: Profit | Z1: Profit % | AA1: Amount | AB1: Profit Amt | AC1: SP Aft + Profit | AE1: Tax | AF1: Tax % | AG1: Tax Amt | AH1: Tax Amt | AJ1: Final Price Aft + Tax
A2: Brand | B2: Category | C2: Sub Category | D2: Product | E2: Size 15mm(½"inch) | F2: 1000 | G2: Pieces | H2: 1.44 | I2: 241 | J2: 2 | K2: 4 | L2: 18 | M2: =ROUND((I2*(1-J2/100))*(1+K2/100)*(1+L2/100),0) | N2: 6 | O2: 60 | R2: =I2 -> 241 | S2: =Template!J2 -> 2 | T2: 0.01 | U2: =S2*T2 -> 0.02 | V2: =U2*R2 -> 4.82 | W2: =R2-V2 -> 236.18 | Y2: =Template!K2 -> 4 | Z2: 0.01 | AA2: =Y2*Z2 -> 0.04 | AB2: =AA2*W2 -> 9.4472 | AC2: =AB2+W2 -> 245.6272 | AE2: =Template!L2 -> 18 | AF2: 0.01 | AG2: =AE2*AF2 -> 0.18 | AH2: =AG2*AC2 -> 44.212896 | AJ2: =AH2+AC2 -> 289.8401
A3: DO NOT CHANGE | B3: DO NOT CHANGE | C3: DO NOT CHANGE | D3: DO NOT CHANGE | E3: Size 20mm(¾"inch) | F3: 1000 | G3: Pieces | H3: 1.87 | I3: 296 | J3: 2 | K3: 4 | L3: 18 | M3: Auto-calc | N3: 6 | O3: 60 | R3: =I3 -> 296 | S3: =Template!J3 -> 2 | T3: 0.01 | U3: =S3*T3 -> 0.02 | V3: =U3*R3 -> 5.92 | W3: =R3-V3 -> 290.08 | Y3: =Template!K3 -> 4 | Z3: 0.01 | AA3: =Y3*Z3 -> 0.04 | AB3: =AA3*W3 -> 11.6032 | AC3: =AB3+W3 -> 301.6832 | AE3: =Template!L3 -> 18 | AF3: 0.01 | AG3: =AE3*AF3 -> 0.18 | AH3: =AG3*AC3 -> 54.302976 | AJ3: =AH3+AC3 -> 355.98618
E4: Size 25mm(1"inch) | F4: 1000 | G4: Pieces | H4: 2.97 | I4: 451 | J4: 2 | K4: 4 | L4: 18 | N4: 6 | O4: 60 | R4: =I4 -> 451 | S4: =Template!J4 -> 2 | T4: 0.01 | U4: =S4*T4 -> 0.02 | V4: =U4*R4 -> 9.02 | W4: =R4-V4 -> 441.98 | Y4: =Template!K4 -> 4 | Z4: 0.01 | AA4: =Y4*Z4 -> 0.04 | AB4: =AA4*W4 -> 17.6792 | AC4: =AB4+W4 -> 459.6592 | AE4: =Template!L4 -> 18 | AF4: 0.01 | AG4: =AE4*AF4 -> 0.18 | AH4: =AG4*AC4 -> 82.738656 | AJ4: =AH4+AC4 -> 542.39786
E5: Size 32mm(1¼"inch) | F5: 1000 | G5: Pieces | H5: 3.84 | I5: 577 | J5: 2 | K5: 4 | L5: 18 | N5: 6 | O5: 60 | R5: =I5 -> 577 | S5: =Template!J5 -> 2 | T5: 0.01 | U5: =S5*T5 -> 0.02 | V5: =U5*R5 -> 11.54 | W5: =R5-V5 -> 565.46 | Y5: =Template!K5 -> 4 | Z5: 0.01 | AA5: =Y5*Z5 -> 0.04 | AB5: =AA5*W5 -> 22.6184 | AC5: =AB5+W5 -> 588.0784 | AE5: =Template!L5 -> 18 | AF5: 0.01 | AG5: =AE5*AF5 -> 0.18 | AH5: =AG5*AC5 -> 105.85411 | AJ5: =AH5+AC5 -> 693.93251
E6: Size 40mm(1½"inch) | F6: 1000 | G6: Pieces | H6: 4.41 | I6: 657 | J6: 2 | K6: 4 | L6: 18 | N6: 6 | O6: 60 | R6: =I6 -> 657 | S6: =Template!J6 -> 2 | T6: 0.01 | U6: =S6*T6 -> 0.02 | V6: =U6*R6 -> 13.14 | W6: =R6-V6 -> 643.86 | Y6: =Template!K6 -> 4 | Z6: 0.01 | AA6: =Y6*Z6 -> 0.04 | AB6: =AA6*W6 -> 25.7544 | AC6: =AB6+W6 -> 669.6144 | AE6: =Template!L6 -> 18 | AF6: 0.01 | AG6: =AE6*AF6 -> 0.18 | AH6: =AG6*AC6 -> 120.53059 | AJ6: =AH6+AC6 -> 790.14499
E7: Size 50mm(2"inch) | F7: 1000 | G7: Pieces | H7: 6.19 | I7: 918 | J7: 2 | K7: 4 | L7: 18 | N7: 6 | O7: 60 | R7: =I7 -> 918 | S7: =Template!J7 -> 2 | T7: 0.01 | U7: =S7*T7 -> 0.02 | V7: =U7*R7 -> 18.36 | W7: =R7-V7 -> 899.64 | Y7: =Template!K7 -> 4 | Z7: 0.01 | AA7: =Y7*Z7 -> 0.04 | AB7: =AA7*W7 -> 35.9856 | AC7: =AB7+W7 -> 935.6256 | AE7: =Template!L7 -> 18 | AF7: 0.01 | AG7: =AE7*AF7 -> 0.18 | AH7: =AG7*AC7 -> 168.41261 | AJ7: =AH7+AC7 -> 1104.0382
E8: Size 65mm(2½"inch) | F8: 1000 | G8: Pieces | H8: 7.93 | I8: 1197 | J8: 2 | K8: 4 | L8: 18 | N8: 6 | O8: 60 | R8: =I8 -> 1197 | S8: =Template!J8 -> 2 | T8: 0.01 | U8: =S8*T8 -> 0.02 | V8: =U8*R8 -> 23.94 | W8: =R8-V8 -> 1173.06 | Y8: =Template!K8 -> 4 | Z8: 0.01 | AA8: =Y8*Z8 -> 0.04 | AB8: =AA8*W8 -> 46.9224 | AC8: =AB8+W8 -> 1219.9824 | AE8: =Template!L8 -> 18 | AF8: 0.01 | AG8: =AE8*AF8 -> 0.18 | AH8: =AG8*AC8 -> 219.59683 | AJ8: =AH8+AC8 -> 1439.5792
E9: Size 80mm(3"inch) | F9: 1000 | G9: Pieces | H9: 10.1 | I9: 1415 | J9: 2 | K9: 4 | L9: 18 | N9: 6 | O9: 60 | R9: =I9 -> 1415 | S9: =Template!J9 -> 2 | T9: 0.01 | U9: =S9*T9 -> 0.02 | V9: =U9*R9 -> 28.3 | W9: =R9-V9 -> 1386.7 | Y9: =Template!K9 -> 4 | Z9: 0.01 | AA9: =Y9*Z9 -> 0.04 | AB9: =AA9*W9 -> 55.468 | AC9: =AB9+W9 -> 1442.168 | AE9: =Template!L9 -> 18 | AF9: 0.01 | AG9: =AE9*AF9 -> 0.18 | AH9: =AG9*AC9 -> 259.59024 | AJ9: =AH9+AC9 -> 1701.7582
E10: Size 100mm(4"inch) | F10: 1000 | G10: Pieces | H10: 14.5 | I10: 2121 | J10: 2 | K10: 4 | L10: 18 | N10: 6 | O10: 60 | R10: =I10 -> 2121 | S10: =Template!J10 -> 2 | T10: 0.01 | U10: =S10*T10 -> 0.02 | V10: =U10*R10 -> 42.42 | W10: =R10-V10 -> 2078.58 | Y10: =Template!K10 -> 4 | Z10: 0.01 | AA10: =Y10*Z10 -> 0.04 | AB10: =AA10*W10 -> 83.1432 | AC10: =AB10+W10 -> 2161.7232 | AE10: =Template!L10 -> 18 | AF10: 0.01 | AG10: =AE10*AF10 -> 0.18 | AH10: =AG10*AC10 -> 389.11018 | AJ10: =AH10+AC10 -> 2550.8334
E11: Size 125mm(5"inch) | F11: 1000 | G11: Pieces | H11: 17.9 | I11: 2667 | J11: 2 | K11: 4 | L11: 18 | N11: 6 | O11: 60 | R11: =I11 -> 2667 | S11: =Template!J11 -> 2 | T11: 0.01 | U11: =S11*T11 -> 0.02 | V11: =U11*R11 -> 53.34 | W11: =R11-V11 -> 2613.66 | Y11: =Template!K11 -> 4 | Z11: 0.01 | AA11: =Y11*Z11 -> 0.04 | AB11: =AA11*W11 -> 104.5464 | AC11: =AB11+W11 -> 2718.2064 | AE11: =Template!L11 -> 18 | AF11: 0.01 | AG11: =AE11*AF11 -> 0.18 | AH11: =AG11*AC11 -> 489.27715 | AJ11: =AH11+AC11 -> 3207.4836
E12: Size 150mm(6"inch) | F12: 1000 | G12: Pieces | H12: 21.2 | I12: 3076 | J12: 2 | K12: 4 | L12: 18 | N12: 6 | O12: 60 | R12: =I12 -> 3076 | S12: =Template!J12 -> 2 | T12: 0.01 | U12: =S12*T12 -> 0.02 | V12: =U12*R12 -> 61.52 | W12: =R12-V12 -> 3014.48 | Y12: =Template!K12 -> 4 | Z12: 0.01 | AA12: =Y12*Z12 -> 0.04 | AB12: =AA12*W12 -> 120.5792 | AC12: =AB12+W12 -> 3135.0592 | AE12: =Template!L12 -> 18 | AF12: 0.01 | AG12: =AE12*AF12 -> 0.18 | AH12: =AG12*AC12 -> 564.31066 | AJ12: =AH12+AC12 -> 3699.3699
